zenircbot_api
