Metadata-Version: 1.1
Name: zenircbot-api
Version: 2.2.4
Summary: API for ZenIRCBot
Home-page: http://zenircbot.rtfd.org/
Author: Wraithan (Chris McDonald)
Author-email: xwraithanx@gmail.com
License: Copyright (C) 2011 by Chris McDonald.
